{
	"title": "Billing Block",
	"features": [
		{
			"id": "info",
			"name": "Information",
			"icon": "icon-info-sign",
			"src": "Symbols or Icons are visually really powerful as they deliver instant information without any cultural or lingual barrier. Icons can support the displayed text or stand on their own."
		},
		{
			"id": "tutorial",
			"name": "Tutorial",
			"icon": "icon-group",
			"src": "tutorial here"
		},
		{
			"id": "test",
			"name": "Testing",
			"icon": "icon-beaker",
			"src": "partials/icon-font_editor.html"
		},
		{
			"id": "resources",
			"name": "Resources",
			"icon": "icon-sitemap",
			"src": "additional resources"
		}
	]
}